hmatch.py
hmatch-1.0.2.dist-info/METADATA
hmatch-1.0.2.dist-info/WHEEL
hmatch-1.0.2.dist-info/entry_points.txt
hmatch-1.0.2.dist-info/top_level.txt
hmatch-1.0.2.dist-info/RECORD
