Metadata-Version: 2.1
Name: hmatch
Version: 1.0.2
Summary: Match HTTP response.
Home-page: https://elis.cc/
Author: Elis
Author-email: me@elis.cc
License: Free License
Keywords: check,website,http,response,match,body,regex,https
Platform: UNKNOWN
Requires-Dist: colorama
